{
  "app.title": "TULOMA-TRACKS: reconstruction",
  "tools.reconstruction": "Reconstruction",
  "reconstruction.btn.load": "Load archive",
  "reconstruction.btn.next": "Next",
  "reconstruction.btn.prev": "Previous",
  "reconstruction.btn.reconstruct": "Reconstruct",
  "reconstruction.btn.trace": "Plot trace",
  "reconstruction.btn.save_traces": "Save traces",
  "reconstruction.btn.save_df": "Save dataframe",

  "reconstruction.sample": "Sampling",
  "reconstruction.sample.draws": "Draws",
  "reconstruction.sample.chains": "Chains",
  "reconstruction.sample.tune": "Tune",
  "reconstruction.sample.random_seed": "Random seed",
  "reconstruction.sample.target_accept": "Target accept",
  "reconstruction.sample.nuts_sampler": "NUTS sampler",


  "reconstruction.form.cutter": "Cutoff",
  "reconstruction.form.cutter.range": "Range",
  "reconstruction.form.cutter.start": "Start",
  "reconstruction.form.cutter.end": "End",

  "reconstruction_model": "Reconstruction model",
  "reconstruction_model.linear": "Linear",
  "reconstruction_model.linear.threshold": "Threshold",
  "reconstruction_model.linear.minv": "Lower velocity [pix/t]",
  "reconstruction_model.linear.maxv": "Upper velocity [pix/t]",

  "reconstruction_model.linear_alt": "Linear (alternative)",
  "reconstruction_model.linear_alt.front_mul": "Front multiplier",
  "reconstruction_model.linear_alt.envelope": "Envelope",
  "reconstruction_model.linear_alt.discrete_time": "Discrete time"
}